{
    "wbDate": "2009-12-25 12:42:54", 
    "title": "Moveable guardian brick (entity)", 
    "oldDumpDate": "2009-12-25 12:42:54", 
    "name": "Moveable_guardian_brick_(entity)", 
    "categories": [
        "Stub", 
        "Entities", 
        "Auto-generated", 
        "Declarations"
    ], 
    "modDate": "2007-10-09 14:14:00", 
    "fileDate": "2009-12-25 12:42:54", 
    "wbUrl": "http://web.archive.org/web/20091225124254/http://www.modwiki.net:80/wiki/Moveable_guardian_brick_%28entity%29"
}
